CRC_Transmitter_Code/CRC_design.sv
// Code your design here
//Design
module task2 #(parameter x=32)			//CRC
  ( output reg [15:0]r,
   output reg [25:0]data_out,
   output reg done,
             input  data,start,clk);
  
  reg [7:0]b;
  always@(posedge clk or posedge start)
    begin
      if(start) begin r<=16'hFFFF;b<=1'b0;done<=1'b0;end
      else if(~done) begin
        r[0]<=data+r[15];
        r[1]<=r[0];
        r[2]<=data+r[1]+r[15];
        r[14:3]<=r[13:2];
        r[15]<=r[14]+r[15]+data;
        b<=b+1;
        if(b>=23)
          begin
            data_out[(x-b+2)*2]<=r[5]^r[4]^r[3]^r[2];
            data_out[(x-b+2)*2+1]<=r[5]^r[4]^r[2];
          end
        if(b==x-1) 
          begin
            done<=1'b1;                       
          end
      end
      else
        begin
          data_out[25]<=r[15]^r[14]^r[12];
          data_out[24]<=r[15]^r[14]^r[13]^r[12];
          data_out[5]<=r[5]^r[4]^r[2];
          data_out[4]<=r[5]^r[4]^r[3]^r[2];
          data_out[3]<=r[4]^r[3]^r[1];
          data_out[2]<=r[4]^r[3]^r[2]^r[1];
          data_out[1]<=r[3]^r[2]^r[0];
          data_out[0]<=r[3]^r[2]^r[1]^r[0];
        end
    end
endmodule

module task3#(parameter x =32, k=4)(output reg [2*x-1:0]fec,
                                    output reg done,
                                    output reg [3:0]r,
                              input data,start,clk);
  reg [7:0] b;
   
  always@(posedge clk or posedge start)
    begin
      if(start) begin r<=0;b<=2*x+2;done<=1'b0;fec<=0;end
      else if(~done)
        begin
          if(b!=2)begin r[0]<=data;
            r[3:1]<=r[2:0];end
          fec[b-2]<=r[3]^r[2]^r[1]^r[0];
          fec[b-1]<=r[3]^r[2]^r[0];
          b<=b-2;
          if(b==2) done<=1'b1;
        end
    end
        
endmodule

module interleaver_4byte (
  input [7:0] byte0,		
  input [7:0] byte1,
  input [7:0] byte2,
  input [7:0] byte3, 
  output [7:0] out0,
  output [7:0] out1,
  output [7:0] out2,
  output [7:0] out3
  );
  assign out3 = {byte3[7:6],byte2[7:6],byte1[7:6],byte0[7:6]};
  assign out2 = {byte3[5:4],byte2[5:4],byte1[5:4],byte0[5:4]};
  assign out1 = {byte3[3:2],byte2[3:2],byte1[3:2],byte0[3:2]};
  assign out0 = {byte3[1:0],byte2[1:0],byte1[1:0],byte0[1:0]};
  
  //always@(*)
  //  begin
  //    for(i=0;i<12;i=i+1)
  //      begin
  //        out[:] =
  //      end
  //  end
  
  
  
endmodule

module interleaver (output [95:0] data_out,
             input [95:0] data_in);
//  assign data_out[95:48]={data_in[3:0],data_in[11:8],data_in[19:16],data_in[27:24],data_in[35:32],data_in[43:40],data_in[51:48],data_in[59:56],data_in[67:64],data_in[75:72],data_in[83:80],data_in[91:88]};
//  assign data_out[47:0]={data_in[7:4],data_in[15:12],data_in[23:20],data_in[31:28],data_in[39:36],data_in[47:44],data_in[55:52],data_in[63:60],data_in[71:68],data_in[79:76],data_in[87:84],data_in[95:92]};
  
  interleaver_4byte IL1 (data_in[31:24],data_in[23:16],data_in[15:8],data_in[7:0],data_out[31:24],data_out[23:16],data_out[15:8],data_out[7:0]);
  interleaver_4byte IL2 (data_in[63:56],data_in[55:48],data_in[47:40],data_in[39:32],data_out[63:56],data_out[55:48],data_out[47:40],data_out[39:32]);
  interleaver_4byte IL3 (data_in[95:88],data_in[87:80],data_in[79:72],data_in[71:64],data_out[95:88],data_out[87:80],data_out[79:72],data_out[71:64]);
  
endmodule



module task4_2(output [95:0] yout, // overall module-fec done in two stages,one while crc is going on, for tthe last 16 bits we can do it parallely through combinational circuit to reduce no. of cycles at cost of more circuitry
               output done,
              input data,start,clk);
  
  wire [15:0]r;
  wire [3:0] last4_data;
  wire [25:0] data_out;
  wire [63:0] fec1;
  wire [95:0] fec2;
  wire done1;
  wire [5:0]b;
  
  task2 T2_2(r,data_out,done1,data,start,clk);
  task3 T3_2(fec1,done,last4_data,data,start,clk);
  interleaver I1(yout,fec2);
  assign b[5]=r[15]^last4_data[2]^last4_data[1];
  assign b[4]=r[15]^last4_data[2]^last4_data[1]^last4_data[0];
  assign b[3]=r[14]^last4_data[1]^last4_data[0];
  assign b[2]=r[15]^r[14]^last4_data[1]^last4_data[0];
  assign b[1]=r[15]^r[13]^last4_data[0];
  assign b[0]=r[15]^r[14]^r[13]^last4_data[0];  
  assign fec2={fec1,b,data_out};
endmodule

CRC_Transmitter_Code/CRC_t.sv
// Code your testbench here
// or browse Examples
//Test Bench
module t_task4_2();
  wire done;
  wire [95:0] yout;
  reg start,clk,data;
  task4_2 T4_2(yout,done,data,start,clk);
  
  initial begin
    clk=1'b0;
    #6 start=1'b0;
    #1 start=1'b1;
    #10 start=1'b0;
  end
  
  always #5 clk=~clk;
  
  initial #1000 $finish;
  initial begin        //Input taken is 32'h03_01_02_03
    #17 data=0;		   
    #10 data=0;
    #10 data=0;
    #10 data=0;//
    #10 data=0;
    #10 data=0;
    #10 data=1;
    #10 data=1;//8
    #10 data=0;
    #10 data=0;
    #10 data=0;
    #10 data=0;//
    #10 data=0;
    #10 data=0;
    #10 data=0;
    #10 data=1;//8
    #10 data=0;
    #10 data=0;
    #10 data=0;
    #10 data=0;//
    #10 data=0;
    #10 data=0;
    #10 data=1;
    #10 data=0;//8
    #10 data=0;
    #10 data=0;
    #10 data=0;
    #10 data=0;//
    #10 data=0;
    #10 data=0;
    #10 data=1;
    #10 data=1;//8
  end
  
  initial begin
    $monitor($time,"- %h , %b , %h",yout,done,T4_2.fec2);
  end
  
  initial begin
    $dumpfile ("t_task4_2.vcd"); $dumpvars (0, t_task4_2);
  end
endmodule

CRC_Transmitter_Code/CRC_t.vcd
$date
	Wed Jul 21 08:09:53 2021
$end
$version
	Icarus Verilog
$end
$timescale
	1s
$end
$scope module t_task4_2 $end
$var wire 1 ! done $end
$var wire 96 " yout [95:0] $end
$var reg 1 # clk $end
$var reg 1 $ data $end
$var reg 1 % start $end
$scope module T4_2 $end
$var wire 6 & b [5:0] $end
$var wire 1 ' clk $end
$var wire 1 ( data $end
$var wire 26 ) data_out [25:0] $end
$var wire 1 ! done $end
$var wire 1 * done1 $end
$var wire 64 + fec1 [63:0] $end
$var wire 96 , fec2 [95:0] $end
$var wire 4 - last4_data [3:0] $end
$var wire 16 . r [15:0] $end
$var wire 1 / start $end
$var wire 96 0 yout [95:0] $end
$scope module T2_2 $end
$var wire 1 ' clk $end
$var wire 1 ( data $end
$var wire 1 / start $end
$var reg 8 1 b [7:0] $end
$var reg 26 2 data_out [25:0] $end
$var reg 1 3 done $end
$var reg 16 4 r [15:0] $end
$upscope $end
$scope module T3_2 $end
$var wire 1 ' clk $end
$var wire 1 ( data $end
$var wire 1 / start $end
$var reg 8 5 b [7:0] $end
$var reg 1 6 done $end
$var reg 64 7 fec [63:0] $end
$var reg 4 8 r [3:0] $end
$upscope $end
$scope module I1 $end
$var wire 96 9 data_in [95:0] $end
$var wire 96 : data_out [95:0] $end
$scope module IL1 $end
$var wire 8 ; byte0 [7:0] $end
$var wire 8 < byte1 [7:0] $end
$var wire 8 = byte2 [7:0] $end
$var wire 8 > byte3 [7:0] $end
$var wire 8 ? out0 [7:0] $end
$var wire 8 @ out1 [7:0] $end
$var wire 8 A out2 [7:0] $end
$var wire 8 B out3 [7:0] $end
$upscope $end
$scope module IL2 $end
$var wire 8 C byte0 [7:0] $end
$var wire 8 D byte1 [7:0] $end
$var wire 8 E byte2 [7:0] $end
$var wire 8 F byte3 [7:0] $end
$var wire 8 G out0 [7:0] $end
$var wire 8 H out1 [7:0] $end
$var wire 8 I out2 [7:0] $end
$var wire 8 J out3 [7:0] $end
$upscope $end
$scope module IL3 $end
$var wire 8 K byte0 [7:0] $end
$var wire 8 L byte1 [7:0] $end
$var wire 8 M byte2 [7:0] $end
$var wire 8 N byte3 [7:0] $end
$var wire 8 O out0 [7:0] $end
$var wire 8 P out1 [7:0] $end
$var wire 8 Q out2 [7:0] $end
$var wire 8 R out3 [7:0] $end
$upscope $end
$upscope $end
$upscope $end
$upscope $end
$enddefinitions $end
#0
$dumpvars
bx R
bx Q
bx P
bx O
bx N
bx M
bx L
bx K
bx J
bx I
bx H
bx G
bx F
bx E
bx D
bx C
bx B
bx A
bx @
bx ?
bx >
bx =
bx <
bx ;
bx :
bx 9
bx 8
bx 7
x6
bx 5
bx 4
x3
bx 2
bx 1
bx 0
x/
bx .
bx -
bx ,
bx +
x*
bx )
x(
0'
bx &
x%
x$
0#
bx "
x!
$end
#5
bx 2
1#
1'
#6
0%
0/
#7
bx11 B
bx10 A
bx01 @
b111001xx ;
b0 J
b0 I
b0 H
b0 G
b0 R
b0 Q
b0 P
b0 O
b0xxxxxxxxxxxxxx01xxxxxx10xxxxxx11 "
b0xxxxxxxxxxxxxx01xxxxxx10xxxxxx11 0
b0xxxxxxxxxxxxxx01xxxxxx10xxxxxx11 :
b111001 &
b0 C
b0 D
b0 E
b0 F
b0 K
b0 L
b0 M
b0 N
b0 7
b111001xxxxxxxxxxxxxxxxxxxxxxxxxx ,
b111001xxxxxxxxxxxxxxxxxxxxxxxxxx 9
b0 +
06
0!
b1000010 5
b0 8
b0 -
03
0*
b0 1
b1111111111111111 4
b1111111111111111 .
1%
1/
#10
0#
0'
#15
1#
1'
#17
0%
0/
0$
0(
#20
0#
0'
#25
bx11 A
bx00 B
bx10 @
b0xxxxxxxxxxxxxx10xxxxxx11xxxxxx00 "
b0xxxxxxxxxxxxxx10xxxxxx11xxxxxx00 0
b0xxxxxxxxxxxxxx10xxxxxx11xxxxxx00 :
b1110xx ;
b1110 &
b1110xxxxxxxxxxxxxxxxxxxxxxxxxx ,
b1110xxxxxxxxxxxxxxxxxxxxxxxxxx 9
b1000000 5
b0 8
b1 1
b111111111111011 .
b111111111111011 4
1#
1'
#30
0#
0'
#35
bx10 A
bx11 B
bx01 @
b0xxxxxxxxxxxxxx01xxxxxx10xxxxxx11 "
b0xxxxxxxxxxxxxx01xxxxxx10xxxxxx11 0
b0xxxxxxxxxxxxxx01xxxxxx10xxxxxx11 :
b111001xx ;
b111001 &
b111001xxxxxxxxxxxxxxxxxxxxxxxxxx ,
b111001xxxxxxxxxxxxxxxxxxxxxxxxxx 9
b10 1
b1111111111110110 4
b1111111111110110 .
b111110 5
b0 7
b0 8
1#
1'
#40
0#
0'
#45
bx11 A
bx00 B
bx10 @
b0xxxxxxxxxxxxxx10xxxxxx11xxxxxx00 "
b0xxxxxxxxxxxxxx10xxxxxx11xxxxxx00 0
b0xxxxxxxxxxxxxx10xxxxxx11xxxxxx00 :
b1110xx ;
b1110 &
b1110xxxxxxxxxxxxxxxxxxxxxxxxxx ,
b1110xxxxxxxxxxxxxxxxxxxxxxxxxx 9
b111100 5
b0 7
b0 8
b11 1
b111111111101001 4
b111111111101001 .
1#
1'
#50
0#
0'
#55
bx10 A
bx11 B
bx01 @
b0xxxxxxxxxxxxxx01xxxxxx10xxxxxx11 "
b0xxxxxxxxxxxxxx01xxxxxx10xxxxxx11 0
b0xxxxxxxxxxxxxx01xxxxxx10xxxxxx11 :
b111001xx ;
b111001 &
b111001xxxxxxxxxxxxxxxxxxxxxxxxxx ,
b111001xxxxxxxxxxxxxxxxxxxxxxxxxx 9
b100 1
b1111111111010010 4
b1111111111010010 .
b111010 5
b0 7
b0 8
1#
1'
#60
0#
0'
#65
bx11 A
bx00 B
bx10 @
b0xxxxxxxxxxxxxx10xxxxxx11xxxxxx00 "
b0xxxxxxxxxxxxxx10xxxxxx11xxxxxx00 0
b0xxxxxxxxxxxxxx10xxxxxx11xxxxxx00 :
b1110xx ;
b1110 &
b1110xxxxxxxxxxxxxxxxxxxxxxxxxx ,
b1110xxxxxxxxxxxxxxxxxxxxxxxxxx 9
b111000 5
b0 7
b0 8
b101 1
b111111110100001 4
b111111110100001 .
1#
1'
#70
0#
0'
#75
bx10 A
bx11 B
bx01 @
b0xxxxxxxxxxxxxx01xxxxxx10xxxxxx11 "
b0xxxxxxxxxxxxxx01xxxxxx10xxxxxx11 0
b0xxxxxxxxxxxxxx01xxxxxx10xxxxxx11 :
b111001xx ;
b111001 &
b111001xxxxxxxxxxxxxxxxxxxxxxxxxx ,
b111001xxxxxxxxxxxxxxxxxxxxxxxxxx 9
b110 1
b1111111101000010 4
b1111111101000010 .
b110110 5
b0 7
b0 8
1#
1'
#77
1$
1(
#80
0#
0'
#85
bx10 B
bx01 A
bx10 @
b0xxxxxxxxxxxxxx10xxxxxx01xxxxxx10 "
b0xxxxxxxxxxxxxx10xxxxxx01xxxxxx10 0
b0xxxxxxxxxxxxxx10xxxxxx01xxxxxx10 :
b100110xx ;
b100110 &
b100110xxxxxxxxxxxxxxxxxxxxxxxxxx ,
b100110xxxxxxxxxxxxxxxxxxxxxxxxxx 9
b110100 5
b0 7
b1 8
b1 -
b111 1
b1111111010000100 .
b1111111010000100 4
1#
1'
#90
0#
0'
#95
bx10 A
bx01 B
b11010xx ;
b1100 P
b1100000000000000000000000000000000000000000000000000xxxxxxxxxxxxxx10xxxxxx10xxxxxx01 "
b1100000000000000000000000000000000000000000000000000xxxxxxxxxxxxxx10xxxxxx10xxxxxx01 0
b1100000000000000000000000000000000000000000000000000xxxxxxxxxxxxxx10xxxxxx10xxxxxx01 :
b11010 &
b1100 L
b1000 1
b1111110100001000 .
b1111110100001000 4
b110010 5
b1100000000000000000000000000000000000000000000000000 7
b1100000000000000000000000000000000000000000000000000011010xxxxxxxxxxxxxxxxxxxxxxxxxx ,
b1100000000000000000000000000000000000000000000000000011010xxxxxxxxxxxxxxxxxxxxxxxxxx 9
b1100000000000000000000000000000000000000000000000000 +
b11 -
b11 8
1#
1'
#97
0$
0(
#100
0#
0'
#105
bx00 B
bx00 A
bx10 @
b10xx ;
b1000 O
b100000001100000000000000000000000000000000000000000000000000xxxxxxxxxxxxxx10xxxxxx00xxxxxx00 "
b100000001100000000000000000000000000000000000000000000000000xxxxxxxxxxxxxx10xxxxxx00xxxxxx00 0
b100000001100000000000000000000000000000000000000000000000000xxxxxxxxxxxxxx10xxxxxx00xxxxxx00 :
b10 &
b1110 L
b110000 5
b1110000000000000000000000000000000000000000000000000000010xxxxxxxxxxxxxxxxxxxxxxxxxx ,
b1110000000000000000000000000000000000000000000000000000010xxxxxxxxxxxxxxxxxxxxxxxxxx 9
b1110000000000000000000000000000000000000000000000000 +
b1110000000000000000000000000000000000000000000000000 7
b110 8
b110 -
b1001 1
b111101000010101 4
b111101000010101 .
1#
1'
#110
0#
0'
#115
bx10 A
bx01 @
bx00 B
b1001xx ;
b100000 R
b100000001100000000000010000000000000000000000000000000000000xxxxxxxxxxxxxx01xxxxxx10xxxxxx00 "
b100000001100000000000010000000000000000000000000000000000000xxxxxxxxxxxxxx01xxxxxx10xxxxxx00 0
b100000001100000000000010000000000000000000000000000000000000xxxxxxxxxxxxxx01xxxxxx10xxxxxx00 :
b1001 &
b10000000 M
b1010 1
b1111010000101010 4
b1111010000101010 .
b101110 5
b1110100000000000000000000000000000000000000000000000001001xxxxxxxxxxxxxxxxxxxxxxxxxx ,
b1110100000000000000000000000000000000000000000000000001001xxxxxxxxxxxxxxxxxxxxxxxxxx 9
b1110100000000000000000000000000000000000000000000000 +
b1110100000000000000000000000000000000000000000000000 7
b1100 -
b1100 8
1#
1'
#120
0#
0'
#125
bx11 A
bx10 @
b100000001100000000000010000000000000000000000000000000000000xxxxxxxxxxxxxx10xxxxxx11xxxxxx00 "
b100000001100000000000010000000000000000000000000000000000000xxxxxxxxxxxxxx10xxxxxx11xxxxxx00 0
b100000001100000000000010000000000000000000000000000000000000xxxxxxxxxxxxxx10xxxxxx11xxxxxx00 :
b1110xx ;
b1110 &
b1110100000000000000000000000000000000000000000000000001110xxxxxxxxxxxxxxxxxxxxxxxxxx ,
b1110100000000000000000000000000000000000000000000000001110xxxxxxxxxxxxxxxxxxxxxxxxxx 9
b101100 5
b1110100000000000000000000000000000000000000000000000 7
b1000 -
b1000 8
b1011 1
b110100001010001 4
b110100001010001 .
1#
1'
#130
0#
0'
#135
bx10 A
bx11 B
bx10 @
b111010xx ;
b111010 &
b111100 P
b100000111100000000000010000000000000000000000000000000000000xxxxxxxxxxxxxx10xxxxxx10xxxxxx11 "
b100000111100000000000010000000000000000000000000000000000000xxxxxxxxxxxxxx10xxxxxx10xxxxxx11 0
b100000111100000000000010000000000000000000000000000000000000xxxxxxxxxxxxxx10xxxxxx10xxxxxx11 :
b10001100 M
b1100 1
b1101000010100010 4
b1101000010100010 .
b101010 5
b1110100011000000000000000000000000000000000000000000 7
b1110100011000000000000000000000000000000000000000000111010xxxxxxxxxxxxxxxxxxxxxxxxxx ,
b1110100011000000000000000000000000000000000000000000111010xxxxxxxxxxxxxxxxxxxxxxxxxx 9
b1110100011000000000000000000000000000000000000000000 +
b0 -
b0 8
1#
1'
#140
0#
0'
#145
bx00 B
bx00 A
bx11 @
b100000111100000000000010000000000000000000000000000000000000xxxxxxxxxxxxxx11xxxxxx00xxxxxx00 "
b100000111100000000000010000000000000000000000000000000000000xxxxxxxxxxxxxx11xxxxxx00xxxxxx00 0
b100000111100000000000010000000000000000000000000000000000000xxxxxxxxxxxxxx11xxxxxx00xxxxxx00 :
b11xx ;
b11 &
b1110100011000000000000000000000000000000000000000000000011xxxxxxxxxxxxxxxxxxxxxxxxxx ,
b1110100011000000000000000000000000000000000000000000000011xxxxxxxxxxxxxxxxxxxxxxxxxx 9
b101000 5
b1110100011000000000000000000000000000000000000000000 7
b0 8
b1101 1
b10000101000001 4
b10000101000001 .
1#
1'
#150
0#
0'
#155
bx11 A
bx01 @
b100000111100000000000010000000000000000000000000000000000000xxxxxxxxxxxxxx01xxxxxx11xxxxxx00 "
b100000111100000000000010000000000000000000000000000000000000xxxxxxxxxxxxxx01xxxxxx11xxxxxx00 0
b100000111100000000000010000000000000000000000000000000000000xxxxxxxxxxxxxx01xxxxxx11xxxxxx00 :
b1101xx ;
b1101 &
b1110100011000000000000000000000000000000000000000000001101xxxxxxxxxxxxxxxxxxxxxxxxxx ,
b1110100011000000000000000000000000000000000000000000001101xxxxxxxxxxxxxxxxxxxxxxxxxx 9
b1110 1
b100001010000010 4
b100001010000010 .
b100110 5
b1110100011000000000000000000000000000000000000000000 7
b0 8
1#
1'
#160
0#
0'
#165
bx11 B
bx01 A
bx11 @
b100000111100000000000010000000000000000000000000000000000000xxxxxxxxxxxxxx11xxxxxx01xxxxxx11 "
b100000111100000000000010000000000000000000000000000000000000xxxxxxxxxxxxxx11xxxxxx01xxxxxx11 0
b100000111100000000000010000000000000000000000000000000000000xxxxxxxxxxxxxx11xxxxxx01xxxxxx11 :
b110111xx ;
b110111 &
b1110100011000000000000000000000000000000000000000000110111xxxxxxxxxxxxxxxxxxxxxxxxxx ,
b1110100011000000000000000000000000000000000000000000110111xxxxxxxxxxxxxxxxxxxxxxxxxx 9
b100100 5
b1110100011000000000000000000000000000000000000000000 7
b0 8
b1111 1
b1000010100000100 .
b1000010100000100 4
1#
1'
#167
1$
1(
#170
0#
0'
#175
bx01 B
bx11 A
bx11 @
b100000111100000000000010000000000000000000000000000000000000xxxxxxxxxxxxxx11xxxxxx11xxxxxx01 "
b100000111100000000000010000000000000000000000000000000000000xxxxxxxxxxxxxx11xxxxxx11xxxxxx01 0
b100000111100000000000010000000000000000000000000000000000000xxxxxxxxxxxxxx11xxxxxx11xxxxxx01 :
b11111xx ;
b11111 &
b1110100011000000000000000000000000000000000000000000011111xxxxxxxxxxxxxxxxxxxxxxxxxx ,
b1110100011000000000000000000000000000000000000000000011111xxxxxxxxxxxxxxxxxxxxxxxxxx 9
b10000 1
b101000001000 .
b101000001000 4
b100010 5
b1110100011000000000000000000000000000000000000000000 7
b1 8
b1 -
1#
1'
#177
0$
0(
#180
0#
0'
#185
bx11 B
bx11 A
bx00 @
b111100xx ;
b11001000 O
b1100100000111100000000000010000000000000000000000000000000000000xxxxxxxxxxxxxx00xxxxxx11xxxxxx11 "
b1100100000111100000000000010000000000000000000000000000000000000xxxxxxxxxxxxxx00xxxxxx11xxxxxx11 0
b1100100000111100000000000010000000000000000000000000000000000000xxxxxxxxxxxxxx00xxxxxx11xxxxxx11 :
b111100 &
b11 N
b100000 5
b1110100011000000001100000000000000000000000000000000 7
b1110100011000000001100000000000000000000000000000000111100xxxxxxxxxxxxxxxxxxxxxxxxxx ,
b1110100011000000001100000000000000000000000000000000111100xxxxxxxxxxxxxxxxxxxxxxxxxx 9
b1110100011000000001100000000000000000000000000000000 +
b10 8
b10 -
b10001 1
b1010000010000 .
b1010000010000 4
1#
1'
#190
0#
0'
#195
bx00 A
bx11 @
b110011xx ;
b110011 &
b1 J
b1100100000111100000000000010000000000000000000000000000000000001xxxxxxxxxxxxxx11xxxxxx00xxxxxx11 "
b1100100000111100000000000010000000000000000000000000000000000001xxxxxxxxxxxxxx11xxxxxx00xxxxxx11 0
b1100100000111100000000000010000000000000000000000000000000000001xxxxxxxxxxxxxx11xxxxxx00xxxxxx11 :
b1000000 C
b10010 1
b10100000100000 .
b10100000100000 4
b11110 5
b1110100011000000001101000000000000000000000000000000 7
b1110100011000000001101000000000000000000000000000000110011xxxxxxxxxxxxxxxxxxxxxxxxxx ,
b1110100011000000001101000000000000000000000000000000110011xxxxxxxxxxxxxxxxxxxxxxxxxx 9
b1110100011000000001101000000000000000000000000000000 +
b100 -
b100 8
1#
1'
#200
0#
0'
#205
bx00 B
bx11 A
bx01 @
b1101xx ;
b1101 &
b11 I
b1100100000111100000000000010000000000000000000000000001100000001xxxxxxxxxxxxxx01xxxxxx11xxxxxx00 "
b1100100000111100000000000010000000000000000000000000001100000001xxxxxxxxxxxxxx01xxxxxx11xxxxxx00 0
b1100100000111100000000000010000000000000000000000000001100000001xxxxxxxxxxxxxx01xxxxxx11xxxxxx00 :
b1110000 C
b11100 5
b1110100011000000001101110000000000000000000000000000 7
b1110100011000000001101110000000000000000000000000000001101xxxxxxxxxxxxxxxxxxxxxxxxxx ,
b1110100011000000001101110000000000000000000000000000001101xxxxxxxxxxxxxxxxxxxxxxxxxx 9
b1110100011000000001101110000000000000000000000000000 +
b1000 -
b1000 8
b10011 1
b101000001000000 .
b101000001000000 4
1#
1'
#210
0#
0'
#215
bx11 B
bx01 A
bx00 @
b110100xx ;
b110100 &
b11 H
b1100100000111100000000000010000000000000000000110000001100000001xxxxxxxxxxxxxx00xxxxxx01xxxxxx11 "
b1100100000111100000000000010000000000000000000110000001100000001xxxxxxxxxxxxxx00xxxxxx01xxxxxx11 0
b1100100000111100000000000010000000000000000000110000001100000001xxxxxxxxxxxxxx00xxxxxx01xxxxxx11 :
b1111100 C
b10100 1
b1010000010000000 .
b1010000010000000 4
b11010 5
b1110100011000000001101111100000000000000000000000000 7
b1110100011000000001101111100000000000000000000000000110100xxxxxxxxxxxxxxxxxxxxxxxxxx ,
b1110100011000000001101111100000000000000000000000000110100xxxxxxxxxxxxxxxxxxxxxxxxxx 9
b1110100011000000001101111100000000000000000000000000 +
b0 -
b0 8
1#
1'
#220
0#
0'
#225
bx10 A
bx10 @
b1100100000111100000000000010000000000000000000110000001100000001xxxxxxxxxxxxxx10xxxxxx10xxxxxx11 "
b1100100000111100000000000010000000000000000000110000001100000001xxxxxxxxxxxxxx10xxxxxx10xxxxxx11 0
b1100100000111100000000000010000000000000000000110000001100000001xxxxxxxxxxxxxx10xxxxxx10xxxxxx11 :
b111010xx ;
b111010 &
b1110100011000000001101111100000000000000000000000000111010xxxxxxxxxxxxxxxxxxxxxxxxxx ,
b1110100011000000001101111100000000000000000000000000111010xxxxxxxxxxxxxxxxxxxxxxxxxx 9
b11000 5
b1110100011000000001101111100000000000000000000000000 7
b0 8
b10101 1
b1100000100000101 4
b1100000100000101 .
1#
1'
#230
0#
0'
#235
bx00 B
bx00 A
bx00 @
b1100100000111100000000000010000000000000000000110000001100000001xxxxxxxxxxxxxx00xxxxxx00xxxxxx00 "
b1100100000111100000000000010000000000000000000110000001100000001xxxxxxxxxxxxxx00xxxxxx00xxxxxx00 0
b1100100000111100000000000010000000000000000000110000001100000001xxxxxxxxxxxxxx00xxxxxx00xxxxxx00 :
b0xx ;
b0 &
b1110100011000000001101111100000000000000000000000000000000xxxxxxxxxxxxxxxxxxxxxxxxxx ,
b1110100011000000001101111100000000000000000000000000000000xxxxxxxxxxxxxxxxxxxxxxxxxx 9
b10110 1
b1000001111 .
b1000001111 4
b10110 5
b1110100011000000001101111100000000000000000000000000 7
b0 8
1#
1'
#237
1$
1(
#240
0#
0'
#245
bx10 B
bx10 A
bx00 @
b1100100000111100000000000010000000000000000000110000001100000001xxxxxxxxxxxxxx00xxxxxx10xxxxxx10 "
b1100100000111100000000000010000000000000000000110000001100000001xxxxxxxxxxxxxx00xxxxxx10xxxxxx10 0
b1100100000111100000000000010000000000000000000110000001100000001xxxxxxxxxxxxxx00xxxxxx10xxxxxx10 :
b101000xx ;
b101000 &
b1110100011000000001101111100000000000000000000000000101000xxxxxxxxxxxxxxxxxxxxxxxxxx ,
b1110100011000000001101111100000000000000000000000000101000xxxxxxxxxxxxxxxxxxxxxxxxxx 9
b10100 5
b1110100011000000001101111100000000000000000000000000 7
b1 8
b1 -
b10111 1
b1000010000011011 .
b1000010000011011 4
1#
1'
#247
0$
0(
#250
0#
0'
#255
bx10 A
bx11 @
b1011xx ;
bx1000 B
b1111 H
b1100100000111100000000000010000000000000000011110000001100000001xxxxxxxxxxxxxx11xxxxxx10xxxx1000 "
b1100100000111100000000000010000000000000000011110000001100000001xxxxxxxxxxxxxx11xxxxxx10xxxx1000 0
b1100100000111100000000000010000000000000000011110000001100000001xxxxxxxxxxxxxx11xxxxxx10xxxx1000 :
b1011 &
b10xxxxxx <
b1100 D
bx10xxxxxxxxxxxxxxxxxxxxxx 2
bx10xxxxxxxxxxxxxxxxxxxxxx )
b11000 1
b1000100000110011 .
b1000100000110011 4
b10010 5
b1110100011000000001101111100000011000000000000000000 7
b1110100011000000001101111100000011000000000000000000001011xx10xxxxxxxxxxxxxxxxxxxxxx ,
b1110100011000000001101111100000011000000000000000000001011xx10xxxxxxxxxxxxxxxxxxxxxx 9
b1110100011000000001101111100000011000000000000000000 +
b10 8
b10 -
1#
1'
#260
0#
0'
#265
b111xx ;
b111 &
b100 G
bx0001 A
b1100100000111100000000000010000000000100000011110000001100000001xxxxxxxxxxxxxx11xxxx0001xxxx1000 "
b1100100000111100000000000010000000000100000011110000001100000001xxxxxxxxxxxxxx11xxxx0001xxxx1000 0
b1100100000111100000000000010000000000100000011110000001100000001xxxxxxxxxxxxxx11xxxx0001xxxx1000 :
b1101 D
b1000xxxx <
b10000 5
b1110100011000000001101111100000011010000000000000000 7
b1110100011000000001101111100000011010000000000000000 +
b100 -
b100 8
bx1000xxxxxxxxxxxxxxxxxxxx 2
b1110100011000000001101111100000011010000000000000000000111xx1000xxxxxxxxxxxxxxxxxxxx ,
b1110100011000000001101111100000011010000000000000000000111xx1000xxxxxxxxxxxxxxxxxxxx 9
bx1000xxxxxxxxxxxxxxxxxxxx )
b11001 1
b1001000001100011 .
b1001000001100011 4
1#
1'
#270
0#
0'
#275
bx1011 B
b110100xx ;
b110100 &
bx1100 @
b110001 J
b1100100000111100000000000010000000000100000011110000001100110001xxxxxxxxxxxx1100xxxx0001xxxx1011 "
b1100100000111100000000000010000000000100000011110000001100110001xxxxxxxxxxxx1100xxxx0001xxxx1011 0
b1100100000111100000000000010000000000100000011110000001100110001xxxxxxxxxxxx1100xxxx0001xxxx1011 :
b100011xx <
b11000000 E
bx100011xxxxxxxxxxxxxxxxxx 2
bx100011xxxxxxxxxxxxxxxxxx )
b11010 1
b1010000011000011 .
b1010000011000011 4
b1110 5
b1110100011000000001101111100000011011100000000000000 7
b1110100011000000001101111100000011011100000000000000110100xx100011xxxxxxxxxxxxxxxxxx ,
b1110100011000000001101111100000011011100000000000000110100xx100011xxxxxxxxxxxxxxxxxx 9
b1110100011000000001101111100000011011100000000000000 +
b1000 -
b1000 8
1#
1'
#280
0#
0'
#285
bx0010 A
bx1110 @
b111010xx ;
b111010 &
b110011 I
bx00xx ?
b1100100000111100000000000010000000000100000011110011001100110001xxxx00xxxxxx1110xxxx0010xxxx1011 "
b1100100000111100000000000010000000000100000011110011001100110001xxxx00xxxxxx1110xxxx0010xxxx1011 0
b1100100000111100000000000010000000000100000011110011001100110001xxxx00xxxxxx1110xxxx0010xxxx1011 :
b11110000 E
b10001100 <
b1100 5
b1110100011000000001101111100000011011111000000000000 7
b1110100011000000001101111100000011011111000000000000 +
b0 -
b0 8
bx10001100xxxxxxxxxxxxxxxx 2
b1110100011000000001101111100000011011111000000000000111010xx10001100xxxxxxxxxxxxxxxx ,
b1110100011000000001101111100000011011111000000000000111010xx10001100xxxxxxxxxxxxxxxx 9
bx10001100xxxxxxxxxxxxxxxx )
b11011 1
b1100000110000011 .
b1100000110000011 4
1#
1'
#290
0#
0'
#295
bx0000 A
bx1100 @
b0xx ;
b0 &
bx001000 B
b1100100000111100000000000010000000000100000011110011001100110001xxxx00xxxxxx1100xxxx0000xx001000 "
b1100100000111100000000000010000000000100000011110011001100110001xxxx00xxxxxx1100xxxx0000xx001000 0
b1100100000111100000000000010000000000100000011110011001100110001xxxx00xxxxxx1100xxxx0000xx001000 :
b0xxxxxx =
bx1000110000xxxxxxxxxxxxxx 2
b1110100011000000001101111100000011011111000000000000000000xx1000110000xxxxxxxxxxxxxx ,
b1110100011000000001101111100000011011111000000000000000000xx1000110000xxxxxxxxxxxxxx 9
bx1000110000xxxxxxxxxxxxxx )
b11100 1
b1100000011 .
b1100000011 4
b1010 5
b1110100011000000001101111100000011011111000000000000 7
b0 8
1#
1'
#300
0#
0'
